TheanoZhongwenWendang0920170304/README.md
TheanoZhongwenWendang0920170304/__init__.py
TheanoZhongwenWendang0920170304/__main__.py
TheanoZhongwenWendang0920170304/file.epub
TheanoZhongwenWendang0920170304/index.html
TheanoZhongwenWendang0920170304/css/__init__.py
TheanoZhongwenWendang0920170304/css/annotations.css
TheanoZhongwenWendang0920170304/css/main.css
TheanoZhongwenWendang0920170304/css/normalize.css
TheanoZhongwenWendang0920170304/css/popup.css
TheanoZhongwenWendang0920170304/font/__init__.py
TheanoZhongwenWendang0920170304/font/fontello.eot
TheanoZhongwenWendang0920170304/font/fontello.svg
TheanoZhongwenWendang0920170304/font/fontello.ttf
TheanoZhongwenWendang0920170304/font/fontello.woff
TheanoZhongwenWendang0920170304/img/__init__.py
TheanoZhongwenWendang0920170304/img/annotator-glyph-sprite.png
TheanoZhongwenWendang0920170304/img/annotator-icon-sprite.png
TheanoZhongwenWendang0920170304/img/apple-touch-icon.png
TheanoZhongwenWendang0920170304/img/cancelfullscreen.png
TheanoZhongwenWendang0920170304/img/close.png
TheanoZhongwenWendang0920170304/img/fullscreen.png
TheanoZhongwenWendang0920170304/img/loader.gif
TheanoZhongwenWendang0920170304/img/menu-icon.png
TheanoZhongwenWendang0920170304/img/save.png
TheanoZhongwenWendang0920170304/img/saved.png
TheanoZhongwenWendang0920170304/img/settings-s.png
TheanoZhongwenWendang0920170304/img/settings.png
TheanoZhongwenWendang0920170304/img/star.png
TheanoZhongwenWendang0920170304/js/__init__.py
TheanoZhongwenWendang0920170304/js/epub.js
TheanoZhongwenWendang0920170304/js/epub.min.js
TheanoZhongwenWendang0920170304/js/epub.min.map
TheanoZhongwenWendang0920170304/js/hooks.min.js
TheanoZhongwenWendang0920170304/js/hooks.min.map
TheanoZhongwenWendang0920170304/js/reader.js
TheanoZhongwenWendang0920170304/js/reader.js.map
TheanoZhongwenWendang0920170304/js/reader.min.js
TheanoZhongwenWendang0920170304/js/reader.min.map
TheanoZhongwenWendang0920170304/js/hooks/__init__.py
theano_zhongwen_wendang_0_9_20170304-2024.3.2.0.dist-info/METADATA
theano_zhongwen_wendang_0_9_20170304-2024.3.2.0.dist-info/WHEEL
theano_zhongwen_wendang_0_9_20170304-2024.3.2.0.dist-info/entry_points.txt
theano_zhongwen_wendang_0_9_20170304-2024.3.2.0.dist-info/top_level.txt
theano_zhongwen_wendang_0_9_20170304-2024.3.2.0.dist-info/RECORD
